{
  "type": "forge:conditional",
  "recipes": [
    {
      "conditions": [
        {
          "type": "blueprint:and",
          "values": [
            {
              "type": "forge:mod_loaded",
              "modid": "woodworks"
            },
            {
              "type": "woodworks:config",
              "value": "wooden_bookshelves"
            }
          ]
        }
      ],
      "recipe": {
        "type": "minecraft:crafting_shaped",
        "category": "building",
        "key": {
          "#": {
            "item": "environmental:plum_planks"
          },
          "X": {
            "item": "environmental:plum_slab"
          }
        },
        "pattern": [
          "###",
          "XXX",
          "###"
        ],
        "result": {
          "item": "minecraft:birch_stairs"
        },
        "show_notification": true
      }
    }
  ]
}